{"event": {"eventState": {}, "tournament": {"name": "Sokak Lig 34, Group A", "slug": "sokak-lig-34", "category": {"name": "Turkey Amateur", "slug": "turkey-amateur", "sport": {"name": "Football", "slug": "football", "id": 1}, "id": 254, "country": {"alpha2": "TR", "alpha3": "TUR", "name": "T\u00fcrkiye", "slug": "turkiye"}, "flag": "turkey", "alpha2": "TR", "fieldTranslations": {"nameTranslation": {"ar": "\u062a\u0631\u0643\u064a\u0627 \u0647\u0648\u0627\u0629"}, "shortNameTranslation": {}}}, "uniqueTournament": {"name": "Sokak Lig 34", "slug": "sokak-lig-34", "category": {"name": "Turkey Amateur", "slug": "turkey-amateur", "sport": {"name": "Football", "slug": "football", "id": 1}, "id": 254, "country": {"alpha2": "TR", "alpha3": "TUR", "name": "T\u00fcrkiye", "slug": "turkiye"}, "flag": "turkey", "alpha2": "TR", "fieldTranslations": {"nameTranslation": {"ar": "\u062a\u0631\u0643\u064a\u0627 \u0647\u0648\u0627\u0629"}, "shortNameTranslation": {}}}, "userCount": 33, "hasRounds": true, "hasPerformanceGraphFeature": false, "id": 30397, "country": {}, "hasEventPlayerStatistics": false, "displayInverseHomeAwayTeams": false, "fieldTranslations": {"nameTranslation": {"ar": "\u062f\u0648\u0631\u064a \u0627\u0644\u0634\u0627\u0631\u0639 34"}, "shortNameTranslation": {}}}, "priority": 0, "isGroup": true, "groupName": "Group A", "competitionType": 1, "id": 167013, "fieldTranslations": {"nameTranslation": {"ar": "\u062f\u0648\u0631\u064a \u0633\u0648\u0643\u0648\u0643 34"}, "shortNameTranslation": {}}}, "season": {"name": "25/26", "year": "25/26", "editor": true, "id": 85096}, "roundInfo": {"round": 3}, "customId": "ocWisNyfj", "status": {"code": 100, "description": "Ended", "type": "finished"}, "winnerCode": 2, "homeTeam": {"name": "Istanbul FC", "slug": "uhud-fc", "shortName": " Istanbul FC", "gender": "M", "sport": {"name": "Football", "slug": "football", "id": 1}, "userCount": 41, "nameCode": "UFC", "disabled": false, "national": false, "type": 0, "id": 1115114, "country": {"alpha2": "TR", "alpha3": "TUR", "name": "T\u00fcrkiye", "slug": "turkiye"}, "fullName": "Istanbul FC", "subTeams": [], "teamColors": {"primary": "#374df5", "secondary": "#374df5", "text": "#ffffff"}, "fieldTranslations": {"nameTranslation": {"ar": "\u0623\u062d\u062f \u0625\u0641 \u0633\u064a"}, "shortNameTranslation": {"ar": "\u0623. \u0633\u064a"}}, "createdByEditor": true, "timeActive": []}, "awayTeam": {"name": "Metro City", "slug": "metro-city", "shortName": "Metro City ", "gender": "M", "sport": {"name": "Football", "slug": "football", "id": 1}, "userCount": 17, "nameCode": "MCI", "disabled": false, "national": false, "type": 0, "id": 1138688, "country": {"alpha2": "TR", "alpha3": "TUR", "name": "T\u00fcrkiye", "slug": "turkiye"}, "fullName": "Metro City", "subTeams": [], "teamColors": {"primary": "#374df5", "secondary": "#374df5", "text": "#ffffff"}, "fieldTranslations": {"nameTranslation": {"ar": "\u0645\u064a\u062a\u0631\u0648 \u0633\u064a\u062a\u064a"}, "shortNameTranslation": {"ar": "\u0645\u064a\u062a\u0631\u0648 \u0633\u064a\u062a\u064a"}}, "createdByEditor": true, "timeActive": []}, "homeScore": {"current": 1, "display": 1, "period1": 1, "period2": 0, "normaltime": 1}, "awayScore": {"current": 2, "display": 2, "period1": 1, "period2": 1, "normaltime": 2}, "coverage": -1, "time": {"period1StartTimestamp": 1767040597, "period2StartTimestamp": 1767042336}, "changes": {"changes": ["status.code", "status.description", "status.type", "time.currentPeriodStart"], "changeTimestamp": 1767044164}, "hasGlobalHighlights": false, "crowdsourcingDataDisplayEnabled": false, "id": 15292141, "defaultPeriodCount": 2, "defaultPeriodLength": 25, "defaultOvertimeLength": 15, "slug": "metro-city-istanbul-fc", "startTimestamp": 1767038409, "finalResultOnly": false, "feedLocked": false, "createdByNickname": "Sokak Lig", "eventEditorName": "Sokak Lig", "eventEditor": {"id": "686d4e3fa63dd9ad3ff166c9", "name": "Sokak Lig"}, "showTotoPromo": true, "isEditor": true}}